README.md
pyproject.toml
setup.cfg
setup.py
spacetower_orbital_state_management/__init__.py
spacetower_orbital_state_management/api_client.py
spacetower_orbital_state_management/api_response.py
spacetower_orbital_state_management/configuration.py
spacetower_orbital_state_management/exceptions.py
spacetower_orbital_state_management/py.typed
spacetower_orbital_state_management/rest.py
spacetower_orbital_state_management.egg-info/PKG-INFO
spacetower_orbital_state_management.egg-info/SOURCES.txt
spacetower_orbital_state_management.egg-info/dependency_links.txt
spacetower_orbital_state_management.egg-info/requires.txt
spacetower_orbital_state_management.egg-info/top_level.txt
spacetower_orbital_state_management/api/__init__.py
spacetower_orbital_state_management/api/default_api.py
spacetower_orbital_state_management/models/__init__.py
spacetower_orbital_state_management/models/anomaly_type.py
spacetower_orbital_state_management/models/atmosphere_model.py
spacetower_orbital_state_management/models/atmosphere_type.py
spacetower_orbital_state_management/models/atmospheric_drag_perturbation.py
spacetower_orbital_state_management/models/attitude_law.py
spacetower_orbital_state_management/models/attitude_law_type.py
spacetower_orbital_state_management/models/battery_model.py
spacetower_orbital_state_management/models/box_object.py
spacetower_orbital_state_management/models/cartesian_covariance_frame_id.py
spacetower_orbital_state_management/models/cartesian_covariance_matrix.py
spacetower_orbital_state_management/models/cartesian_orbit.py
spacetower_orbital_state_management/models/celestial_body_name.py
spacetower_orbital_state_management/models/circular_orbit.py
spacetower_orbital_state_management/models/covariance_orbit_type.py
spacetower_orbital_state_management/models/earth_centered_frame_id.py
spacetower_orbital_state_management/models/earth_oriented_maneuver_attitude_law.py
spacetower_orbital_state_management/models/earth_potential_perturbation.py
spacetower_orbital_state_management/models/equinoctial_orbit.py
spacetower_orbital_state_management/models/fixed_step_integrator_configuration.py
spacetower_orbital_state_management/models/fixed_step_integrator_type.py
spacetower_orbital_state_management/models/harris_priester_atmosphere.py
