Metadata-Version: 2.1
Name: spacetower_orbital_state_management
Version: 1.0.0
Summary: Orbital State Management API
Home-page: 
Author: OpenAPI Generator community
Author-email: team@openapitools.org
License: Exotrail
Keywords: OpenAPI,OpenAPI-Generator,Orbital State Management API
Requires-Dist: urllib3<2.1.0,>=1.25.3
Requires-Dist: python-dateutil
Requires-Dist: pydantic>=2
Requires-Dist: typing-extensions>=4.7.1
